plyer/__init__.py
plyer/utils.py
plyer/facades/__init__.py
plyer/facades/accelerometer.py
plyer/facades/audio.py
plyer/facades/barometer.py
plyer/facades/battery.py
plyer/facades/bluetooth.py
plyer/facades/brightness.py
plyer/facades/call.py
plyer/facades/camera.py
plyer/facades/compass.py
plyer/facades/cpu.py
plyer/facades/email.py
plyer/facades/filechooser.py
plyer/facades/flash.py
plyer/facades/gps.py
plyer/facades/gravity.py
plyer/facades/gyroscope.py
plyer/facades/humidity.py
plyer/facades/irblaster.py
plyer/facades/keystore.py
plyer/facades/light.py
plyer/facades/notification.py
plyer/facades/orientation.py
plyer/facades/processors.py
plyer/facades/proximity.py
plyer/facades/screenshot.py
plyer/facades/sms.py
plyer/facades/spatialorientation.py
plyer/facades/storagepath.py
plyer/facades/stt.py
plyer/facades/temperature.py
plyer/facades/tts.py
plyer/facades/uniqueid.py
plyer/facades/vibrator.py
plyer/facades/wifi.py
plyer/platforms/__init__.py
plyer/platforms/android/__init__.py
plyer/platforms/android/accelerometer.py
plyer/platforms/android/audio.py
plyer/platforms/android/barometer.py
plyer/platforms/android/battery.py
plyer/platforms/android/bluetooth.py
plyer/platforms/android/brightness.py
plyer/platforms/android/call.py
plyer/platforms/android/camera.py
plyer/platforms/android/compass.py
plyer/platforms/android/email.py
plyer/platforms/android/filechooser.py
plyer/platforms/android/flash.py
plyer/platforms/android/gps.py
plyer/platforms/android/gravity.py
plyer/platforms/android/gyroscope.py
plyer/platforms/android/humidity.py
plyer/platforms/android/irblaster.py
plyer/platforms/android/keystore.py
plyer/platforms/android/light.py
plyer/platforms/android/notification.py
plyer/platforms/android/orientation.py
plyer/platforms/android/proximity.py
plyer/platforms/android/sms.py
plyer/platforms/android/spatialorientation.py
plyer/platforms/android/storagepath.py
plyer/platforms/android/stt.py
plyer/platforms/android/temperature.py
plyer-2.0.0.dist-info/LICENSE
plyer-2.0.0.dist-info/METADATA
plyer-2.0.0.dist-info/WHEEL
plyer-2.0.0.dist-info/top_level.txt
plyer-2.0.0.dist-info/RECORD
