Metadata-Version: 2.1
Name: plyer
Version: 2.0.0
Summary: Platform-independent wrapper for platform-dependent APIs
Home-page: https://plyer.readthedocs.org/en/latest/
Author: Kivy team
Author-email: mat@kivy.org
License: Copyright (c) 2010-2017 Kivy Team and other contributors
